telegram_admin_informer/__init__.py
telegram_admin_informer-0.1.dist-info/LICENSE
telegram_admin_informer-0.1.dist-info/METADATA
telegram_admin_informer-0.1.dist-info/WHEEL
telegram_admin_informer-0.1.dist-info/top_level.txt
telegram_admin_informer-0.1.dist-info/RECORD
