Metadata-Version: 2.1
Name: telegram-admin-informer
Version: 0.1
Summary: Telegram admin informer
Home-page: https://github.com/yababay/telegram-admin-informer
Download-URL: https://github.com/yababay/telegram-admin-informer/archive/v_01.tar.gz
Author: Михаил Беляков (Michael Belyakov)
Author-email: bigbelk@live.ru
License: MIT
Keywords: telegram,admin
Platform: UNKNOWN
Classifier: Development Status :: 3 - Alpha
Classifier: Intended Audience :: Developers
Classifier: Topic :: Software Development :: Build Tools
Classifier: License :: OSI Approved :: MIT License
Classifier: Programming Language :: Python :: 3.9
License-File: LICENSE
Requires-Dist: requests
